LICENSE
MANIFEST.in
README.md
setup.py
django_transadmin.egg-info/PKG-INFO
django_transadmin.egg-info/SOURCES.txt
django_transadmin.egg-info/dependency_links.txt
django_transadmin.egg-info/not-zip-safe
django_transadmin.egg-info/top_level.txt
transadmin/__init__.py
transadmin/admin.py
transadmin/forms.py
transadmin/helpers.py
transadmin/models.py
transadmin/settings.py
transadmin/tests.py
transadmin/management/__init__.py
transadmin/management/commands/__init__.py
transadmin/management/commands/transadmin_import.py
transadmin/migrations/0001_initial.py
transadmin/migrations/0002_auto__add_field_translation_source_uid.py
transadmin/migrations/__init__.py