Metadata-Version: 1.1
Name: django-transadmin
Version: 0.2.6
Summary: Translate texts from the admin interface.
Home-page: http://github.com/vinyll/django-transadmin
Author: Vincent Agnano
Author-email: vincent.agnano@scopyleft.fr
License: BSD
Platform: UNKNOWN
Classifier: Environment :: Web Environment
Classifier: Intended Audience :: Developers
Classifier: License :: OSI Approved :: BSD License
Classifier: Operating System :: OS Independent
Classifier: Programming Language :: Python
Classifier: Programming Language :: Python :: 2.5
Classifier: Programming Language :: Python :: 2.6
Classifier: Programming Language :: Python :: 2.7
Classifier: Topic :: Software Development :: Internationalization
Classifier: Topic :: Utilities
